{"allTokens": [{"tokenIndex": 0, "text": "Clinica CardioPlus", "confidence": 1.0, "boundingBox": {"x": 0.10500000072916668, "y": 0.9187500002864584, "width": 0.18166666666666667, "height": 0.022916666666666585}, "pageIndex": 0, "blockIndex": 0, "lineIndex": 0, "isBoundingBoxApproximate": false}, {"tokenIndex": 1, "text": "Secția relevantă", "confidence": 1.0, "boundingBox": {"x": 0.11499999925, "y": 0.8812499997083334, "width": 0.16166666666666668, "height": 0.029166666666666563}, "pageIndex": 0, "blockIndex": 0, "lineIndex": 0, "isBoundingBoxApproximate": false}, {"tokenIndex": 2, "text": "10.04.2025", "confidence": 1.0, "boundingBox": {"x": 0.13823998627504186, "y": 0.8534875590905238, "width": 0.11352002461751304, "height": 0.02635821501413982}, "pageIndex": 0, "blockIndex": 0, "lineIndex": 0, "isBoundingBoxApproximate": false}, {"tokenIndex": 3, "text": "SCRISOARE MEDICALĂ /", "confidence": 1.0, "boundingBox": {"x": 0.4166666704444445, "y": 0.89791666625, "width": 0.4666666666666667, "height": 0.050000000000000044}, "pageIndex": 0, "blockIndex": 0, "lineIndex": 0, "isBoundingBoxApproximate": false}, {"tokenIndex": 4, "text": "BILET DE EXTERNARE", "confidence": 1.0, "boundingBox": {"x": 0.4166666692708333, "y": 0.83333333359375, "width": 0.41666666666666663, "height": 0.05208333333333337}, "pageIndex": 0, "blockIndex": 0, "lineIndex": 0, "isBoundingBoxApproximate": false}, {"tokenIndex": 5, "text": "Nume:George Enache", "confidence": 1.0, "boundingBox": {"x": 0.038333334999999975, "y": 0.7354166669494048, "width": 0.29333333333333333, "height": 0.039583333333333304}, "pageIndex": 0, "blockIndex": 0, "lineIndex": 0, "isBoundingBoxApproximate": false}, {"tokenIndex": 6, "text": "AdresăStr. Florilor nr. 28, Tecuci", "confidence": 1.0, "boundingBox": {"x": 0.03666666417708337, "y": 0.6729166664973958, "width": 0.3983333333333333, "height": 0.039583333333333415}, "pageIndex": 0, "blockIndex": 0, "lineIndex": 0, "isBoundingBoxApproximate": false}, {"tokenIndex": 7, "text": "Vârstă: 37 ani", "confidence": 1.0, "boundingBox": {"x": 0.5790910730955074, "y": 0.7286900106766085, "width": 0.20848452250162763, "height": 0.05303664803504948}, "pageIndex": 0, "blockIndex": 0, "lineIndex": 0, "isBoundingBoxApproximate": false}, {"tokenIndex": 8, "text": "CNP: 1880823104463", "confidence": 1.0, "boundingBox": {"x": 0.5850000017083332, "y": 0.6729166668489583, "width": 0.27333333333333343, "height": 0.03749999999999998}, "pageIndex": 0, "blockIndex": 0, "lineIndex": 0, "isBoundingBoxApproximate": false}, {"tokenIndex": 9, "text": "Anamneză: Pacient internat pentru evaluare și tratament, cu", "confidence": 1.0, "boundingBox": {"x": 0.036666671489583254, "y": 0.5687500001302084, "width": 0.7716666666666667, "height": 0.03749999999999987}, "pageIndex": 0, "blockIndex": 0, "lineIndex": 0, "isBoundingBoxApproximate": false}, {"tokenIndex": 10, "text": "simptomatologie recent accentuată.", "confidence": 1.0, "boundingBox": {"x": 0.23666666965476188, "y": 0.5333333333482143, "width": 0.41833333333333333, "height": 0.03541666666666665}, "pageIndex": 0, "blockIndex": 0, "lineIndex": 0, "isBoundingBoxApproximate": false}, {"tokenIndex": 11, "text": "Diagnostic: Sindrom vertiginos periferic (H81.3)", "confidence": 1.0, "boundingBox": {"x": 0.039999996968750035, "y": 0.46458333304687494, "width": 0.6183333333333334, "height": 0.04583333333333339}, "pageIndex": 0, "blockIndex": 0, "lineIndex": 0, "isBoundingBoxApproximate": false}, {"tokenIndex": 12, "text": "Recomandărfontinuarea tratamentului prescris, control ambulator și", "confidence": 1.0, "boundingBox": {"x": 0.03999999567500007, "y": 0.41041666654166664, "width": 0.865, "height": 0.03750000000000009}, "pageIndex": 0, "blockIndex": 0, "lineIndex": 0, "isBoundingBoxApproximate": false}, {"tokenIndex": 13, "text": "monitorizare clinică.", "confidence": 1.0, "boundingBox": {"x": 0.236547466532097, "y": 0.3790490655625267, "width": 0.24532524108886714, "height": 0.03452531894048061}, "pageIndex": 0, "blockIndex": 0, "lineIndex": 0, "isBoundingBoxApproximate": false}, {"tokenIndex": 14, "text": "Tratament la externare:", "confidence": 1.0, "boundingBox": {"x": 0.03333333013888894, "y": 0.3020833331163194, "width": 0.3833333333333333, "height": 0.046875}, "pageIndex": 0, "blockIndex": 0, "lineIndex": 0, "isBoundingBoxApproximate": false}, {"tokenIndex": 15, "text": "1. Magneziu 375 mg - 1 cp/zi", "confidence": 1.0, "boundingBox": {"x": 0.05500000276388884, "y": 0.26666666685763885, "width": 0.33166666666666667, "height": 0.03541666666666665}, "pageIndex": 0, "blockIndex": 0, "lineIndex": 0, "isBoundingBoxApproximate": false}, {"tokenIndex": 16, "text": "2. Piracetam 800 mg - 1 cp de 2 ori/zi", "confidence": 1.0, "boundingBox": {"x": 0.05333333641666665, "y": 0.23125000016369046, "width": 0.43166666666666664, "height": 0.03541666666666665}, "pageIndex": 0, "blockIndex": 0, "lineIndex": 0, "isBoundingBoxApproximate": false}, {"tokenIndex": 17, "text": "DR. MATEI SORIN", "confidence": 1.0, "boundingBox": {"x": 0.7449999978125, "y": 0.1187499999479168, "width": 0.17499999999999993, "height": 0.02499999999999991}, "pageIndex": 0, "blockIndex": 0, "lineIndex": 0, "isBoundingBoxApproximate": false}, {"tokenIndex": 18, "text": "Medic Specialist Cardiologie", "confidence": 1.0, "boundingBox": {"x": 0.6916666647142856, "y": 0.08541666687499994, "width": 0.2833333333333333, "height": 0.029166666666666674}, "pageIndex": 0, "blockIndex": 0, "lineIndex": 0, "isBoundingBoxApproximate": false}], "pages": [{"pageIndex": 0, "pageWidth": 1.0, "pageHeight": 1.0}], "detectedLanguage": ""}